messages/__init__.py
messages/farewell/Farewell.py
messages/farewell/__init__.py
messages/greeting/Greetings.py
messages/greeting/__init__.py
messages_test_nan-1.4.dist-info/licenses/LICENSE
tests/__init__.py
tests/test_hola.py
messages_test_nan-1.4.dist-info/METADATA
messages_test_nan-1.4.dist-info/WHEEL
messages_test_nan-1.4.dist-info/top_level.txt
messages_test_nan-1.4.dist-info/RECORD
