Metadata-Version: 2.4
Name: messages_test_nan
Version: 1.4
Summary: Un paquete con los mensajes para saludar y despedirse
Home-page: https://www.fb.com/acudnan_
Author: Eduardo Nanduca
Author-email: acudnan@gmail.com
License: MIT License
Classifier: Environment :: Console :: Curses
Classifier: Programming Language :: Python :: 3.13
Classifier: Topic :: Utilities
Classifier: Operating System :: Microsoft :: Windows
License-File: LICENSE
Requires-Dist: numpy>=2.4.0
Dynamic: author
Dynamic: author-email
Dynamic: classifier
Dynamic: description
Dynamic: description-content-type
Dynamic: home-page
Dynamic: license
Dynamic: license-file
Dynamic: requires-dist
Dynamic: summary
